as2s_sparameter/__init__.py
as2s_sparameter/constants.py
as2s_sparameter/interface.py
as2s_sparameter/sparameter.py
as2s_sparameter-0.0.5.dist-info/LICENSE
as2s_sparameter-0.0.5.dist-info/METADATA
as2s_sparameter-0.0.5.dist-info/WHEEL
as2s_sparameter-0.0.5.dist-info/top_level.txt
as2s_sparameter-0.0.5.dist-info/RECORD
